Workbook

Sheet はじめに
A1: STEAM教育・子ども向けプログラミング教室 競合比較（元データ）
A3: 目的 | B3: 社内の戦略検討用。ステモンと主要競合の料金・レッスン内容・講師・教材・課題を網羅的に比較し、打ち手を検討する
A4: 調査日 | B4: 2026-09-28
A5: 対象 | B5: 自社1＋競合13社（ロボット・ものづくり系7、プログラミング特化系3、オンライン・通信系3）＋参考：ナリカ（教材サプライヤー）
A6: 調査方法 | B6: Web検索結果（検索エンジンが表示した公式サイト・比較サイト・口コミサイト・求人サイトの要約）から収集
A7: ⚠ 重要な注意 | B7: 調査環境の制約で各社公式ページの本文は直接閲覧できていない。数値は検索結果の要約ベースのため、社外利用・意思決定の前に「要確認リスト」シートの項目を公式ページで確認すること
A8: 確度の表記 | B8: 公式＝運営会社・公式サイト由来／二次＝比較・口コミ・ブログ由来／推定＝本資料での試算／要確認＝出典が古い・食い違う・一次未確認
A9: 料金の注意 | B9: FC中心のブランドは教室ごとに料金が異なる。総額は「料金比較」シートの前提（C列）に基づく試算
A10: 編集方法 | B10: 「料金比較」シートの青字セル（入会金・月謝・諸費用・教材費・授業時間）を書き換えると、総額・ステモン比・1時間単価・グラフ・サマリーが自動で再計算される
A11: シート構成 | B11: サマリー／料金比較／レッスン・教材／講師／口コミ・課題／ポジショニング／ステモン戦略（SWOT・提言）／要確認リスト／参考_ナリカ・その他／出典

Sheet サマリー
A1: サマリー（全社の主要項目一覧）
A2: 総額は「料金比較」シートと連動。脅威度＝ステモンにとっての競合度合い（高／中／低、定性評価）
A4: 分類 | B4: 社名 | C4: 運営会社 | D4: 対象 | E4: 規模 | F4: 運営形態 | G4: 月謝 | H4: 1年目総額 (試算) | I4: 3年総額 (試算) | J4: 教材（購入/貸与） | K4: 講師（雇用・時給） | L4: 強み（口コミで評価される点） | M4: 主な弱み・課題 | N4: 脅威度
A5: 自社 | B5: ステモン（自社） | C5: 株式会社ヴィリング | D5: 年中〜小6（プロロボは小4〜中学生程度） | E5: 170教室以上（2026年4月）／在籍3,500名以上（要確認） | F5: 直営＋FC（塾併設も多い） | G5: 8,580〜11,880円（＋施設費880〜2,200円） | H5: =料金比較!L5 -> 156420 | I5: =料金比較!M5 -> 464860 | J5: 独自カリキュラム＋ブロック教材＋PC（製品名は要確認）／教室で貸出（購入不要）。PCレンタル2,200円/月 | K5: パート・アルバイト（正社員の教室運営職も募集）／1コマ2,000〜2,700円（時給換算 約1,330〜1,800円）／研修時給1,170〜1,240円 | L5: 体験型で夢中になる、ものの仕組みから学べる、ロボコンに出られる、オリコン顧客満足度 ロボット部門6位（76.4点） | M5: オンライン系の2〜3倍の価格。FCで品質・ルールがばらつく。小4以降の出口（本格的なコード）が薄い。料金表示が情報源でばらつく | N5: —
A6: ロボット・ものづくり | B6: STEAM Campus（旧レゴスクール） | C6: ラーニングシステム ほか地域運営会社（LaZo/SLS、アップ、イマージュ、第一楽器 等） | D6: 2歳〜中学生（中心は年少〜小学生） | E6: 教室総数は不明（首都圏の商業施設中心＋関西・東海） | F6: パートナー制（FCに近い形） | G6: 平均 約11,100円（年齢で段階的に上昇） | H6: =料金比較!L6 -> 188500 | I6: =料金比較!M6 -> 514900 | J6: LEGO Education（既製品）／家庭用教材を毎年購入（年1〜4.7万円） | K6: アルバイト・パート／時給1,200〜1,600円（研修1,120円の例） | L6: 独自性の高いプログラム、幼児期から始められる、商業施設内で通いやすい | M6: 2024年にLEGOブランドを失い認知低下。教材の毎年購入で総額が見えにくい。運営会社が複数で品質・料金にばらつき | N6: 中
A7: ロボット・ものづくり | B7: ヒューマンアカデミー ロボット教室 | C7: ヒューマンアカデミー株式会社（ヒューマンHD） | D7: 年中〜高校生相当 | E7: 2,000教室以上・生徒27,000人超（2025年8月、公式） | F7: FC主体（塾・学童等の併設。加盟金0円） | G7: 全コース一律11,550円 | H7: =料金比較!L7 -> 182600 | I7: =料金比較!M7 -> 479800 | J7: 独自ロボットキット（高橋智隆氏監修）／購入制・持ち帰り可 | K7: 業務委託講師／時給1,320円〜 | L7: 教室が多く近所にある、ロボットがかっこよく夢中になる、テキストが充実、全国大会、月2回で続けやすい | M7: 業務委託・未経験可の講師で品質がばらつく。テキスト通りの組み立て中心。月2回で接触回数が少ない | N7: 高
A8: ロボット・ものづくり | B8: ロボ団 | C8: 夢見る株式会社（大阪） | D8: 年長〜中学生 | E8: 約100〜120教室・生徒5,500〜6,500人（2022年時点、最新値なし） | F8: 直営＋FC（単独型／併設型） | G8: 9,800〜15,800円（コースで異なる） | H8: =料金比較!L8 -> 164000 | I8: =料金比較!M8 -> 470000 | J8: LEGO Education SPIKE Prime＋独自テキスト／教室で貸与（持ち帰り不可）、家庭用タブレットが必要な場合あり | K8: アルバイト（サポート講師）／要確認 | L8: ペアワークと発表でプレゼン力がつく、教材購入不要、アプリで学習状況が分かる、大会がある | M8: 成果物が家に残らず保護者が成長を実感しにくい。料金体系が分かりにくい。規模の開示が2022年で止まっている | N8: 中
A9: ロボット・ものづくり | B9: クレファス（Crefus） | C9: 株式会社ロボット科学教育＋CREFUSマーケティング（中央出版との合弁） | D9: 年長〜高校生（年長〜小2はKicks） | E9: 112教室（時点不明）＋海外（ホーチミン・台北） | F9: 直営＋FC（塾併設が多い） | G9: Kicks 11,000円／本科 17,600円＋維持費1,210円 | H9: =料金比較!L9 -> 310035 | I9: =料金比較!M9 -> 761475 | J9: LEGOベース（LEGO Education/マインドストーム系）＋独自テキスト／購入制（年長・小1・小3・小4の節目で買い足し） | K9: アルバイト講師／時給2,000円以上 | L9: 本格的なカリキュラム、FLL等の大会実績が豊富、中高生まで続けられる、教科と連動 | M9: 3年総額が最も高い部類（推定70万円超）。大会志向で上級者向けの印象。教材の買い替え負担 | N9: 中
A10: ロボット・ものづくり | B10: アーテック エジソンアカデミー | C10: 株式会社アーテック（教材メーカー） | D10: 小3以上（低学年は姉妹コース「自考力キッズ」） | E10: 約850〜900教室（2021年頃の数値、最新は未確認） | F10: FC（塾・PC教室の併設中心） | G10: 8,000〜12,000円程度（教室ごと、本部は非公表） | H10: =料金比較!L10 -> 183000 | I10: =料金比較!M10 -> 447000 | J10: 自社製アーテックロボ／Studuino（Scratchベース）／買い取り制・持ち帰り可 | K10: 加盟教室ごとに採用／要確認 | L10: 料金が比較的安い、少人数、毎月ロボットが完成する達成感、持ち帰って家で遊べる | M10: 対象が小3以上中心。2年で一巡し3年目以降は任意。FCで講師の熱量・専門性が教室依存。料金非公開 | N10: 中
A11: ロボット・ものづくり | B11: プログラボ | C11: プログラボ教育事業運営委員会（ミマモルメ〈阪神電鉄子会社〉＋読売テレビ）。関東は東京メトロと協業 | D11: 年長〜中学生 | E11: 84校・在籍約8,000名（2024年9月） | F11: 直営中心＋FC | G11: 11,770〜14,850円 | H11: =料金比較!L11 -> 141240 | I11: =料金比較!M11 -> 484440 | J11: LEGO Education SPIKE Prime／EV3、micro:bit、Scratch／教室で貸与（持ち帰り不可） | K11: アルバイト（学生歓迎）／時給1,100〜2,000円、研修時給1,200円〜 | L11: 入会金・教材費0円、駅近で通いやすい、講師が多く質問しやすい、WROへの道 | M11: LEGO既製品を組む中心。持ち帰り不可。学生講師中心でばらつき。鉄道沿線に立地が偏る | N11: 高
A12: ロボット・ものづくり | B12: タミヤロボットスクール | C12: 株式会社ナチュラルスタイル（福井）、企画協力：タミヤ | D12: 小学生（下限学年は教室ごと） | E12: 約100教室（古い数値、最新は未確認） | F12: FC | G12: 6,500〜8,500円 | H12: =料金比較!L12 -> 116150 | I12: =料金比較!M12 -> 314150 | J12: タミヤ工作キット＋IchigoJam（既製品）／購入制・持ち帰り可 | K12: 加盟事業者ごとに採用／要確認 | L12: 月謝が業界最安クラス、タミヤブランドの安心感、本物の工作（ギア・モーター）、早期にテキストプログラミング | M12: 教室数が少なく知名度はタミヤ頼み。低学年・未就学への対応が弱い。キット組立中心で自由な発想の比重は限定的 | N12: 低
A13: プログラミング特化 | B13: LITALICOワンダー | C13: 株式会社LITALICO（東証プライム） | D13: 年長〜高3 | E13: 23拠点（2026年6月末）＋オンライン、1都3県のみ | F13: 直営 | G13: 29,700円〜（エキスパート・3DCG 34,100円〜） | H13: =料金比較!L13 -> 372900 | I13: =料金比較!M13 -> 1085700 | J13: Scratch／Viscuit→HTML/JS、LEGO SPIKE、3Dプリンタ・レーザーカッター／教室備品（月謝込み） | K13: 正社員中心＋研修済みアルバイト／アルバイト時給1,230〜1,500円 | L13: 先生の質・子ども理解、少人数・個別対応、好きを伸ばす自由度、設備が充実 | M13: 月3万円前後で家計負担大。拠点が少ない。自由創作型で「何が身についたか」が見えにくい | N13: 低
A14: プログラミング特化 | B14: Tech Kids School | C14: 株式会社CA Tech Kids（サイバーエージェント子会社） | D14: 小学生 | E14: 渋谷校1校＋オンライン校。【新規の体験・入学受付を停止中】 | F14: 直営 | G14: 23,210円＋教材費2,200円（PCレンタル＋4,400円） | H14: =料金比較!L14 -> 304920 | I14: =料金比較!M14 -> 914760 | J14: QUREO、Scratch、Swift、Unity／PC持参 or レンタル | K14: 学生スタッフ（大学生・院生メンター）／要確認 | L14: 本格度（アプリ公開・大会入賞）、発表文化、サイバーエージェントブランド | M14: 新規受付停止（事業縮小・QUREOへのシフトの可能性）。拠点が渋谷のみ。画面内学習に偏る | N14: 低
A15: プログラミング特化 | B15: QUREOプログラミング教室 | C15: 株式会社キュレオ（CA Tech Kids 60%・スプリックス 40%）。各教室は加盟塾が運営 | D15: 小2〜中学生 | E15: 3,000教室超（2024年3月）、最新表記 3,272〜3,300教室 | F15: 加盟（ライセンス）型・学習塾への併設中心 | G15: 9,900円〜（教室ごと） | H15: =料金比較!L15 -> 118800 | I15: =料金比較!M15 -> 356400 | J15: 独自オンライン教材QUREO＋教育版マインクラフト／アカウント型（PC等は教室備品が多い） | K15: 加盟塾の講師／時給1,300〜1,680円程度（求人例） | L15: 月1万円前後で安い、教材費無料、近所の塾で通える、ゲーム感覚、進捗が見える、検定で成果が形に | M15: 加盟塾ごとの講師品質差。画面内完結でハンズオン・協働が少ない。教室体験は塾依存 | N15: 中
A16: オンライン・通信 | B16: Z会プログラミング講座 | C16: 株式会社Z会（増進会HDグループ） | D16: 年長〜中学生（みらい講座 ステージ1は小1〜4） | E16: 通信教育（全国） | F16: 通信（キット＋テキスト） | G16: 約6,200円（KOOVキット代込み） | H16: =料金比較!L16 -> 74400 | I16: =料金比較!M16 -> 230400 | J16: KOOVアドバンスキット（ソニー）、Scratch／キット所有 | K16: 講師なし／— | L16: 自分のペースで学べる、Z会ブランドの教材品質、キットを所有できて割安 | M16: 講座の新規受付終了・統廃合が続く（LEGO講座2023年、中学講座2026年11月）。講師不在で継続は家庭次第 | N16: 低
... A18: オンライン・通信 | B18: CodeCampKIDS | C18: コードキャンプ株式会社（フューチャーグループ） | D18: 年長〜中学生 | E18: 40教室以上＋オンライン | F18: 直営＋FC＋オンライン | G18: 11,000〜16,500円（Online+ 約6,600円） | H18: =料金比較!L18 -> 143000 | I18: =料金比較!M18 -> 539000 | J18: ScratchJr、Scratch、toio、Sphero Mini、Unity／要確認 | K18: アルバイト／時給1,200〜1,500円以上 | L18: 1か月お試しできる、教室がきれい、Unityまで進める出口の高さ | M18: 教室数40強で首都圏中心。上位コースが高額。物理・ものづくり要素は薄い | N18: 低

Sheet 料金比較
A1: 料金比較（1年目・3年継続の総額試算）
A2: 青字＝入力値（書き換え可）／黒字＝数式。金額は税込・円。教材・その他＝各年に一括でかかる費用（教材購入・更新料・大会参加費など）
A4: 分類 | B4: 社名 | C4: 計算の前提 | D4: 入会金 | E4: 月謝 1年目 | F4: 月謝 2年目 | G4: 月謝 3年目 | H4: 月額 諸費用 | I4: 教材・その他 1年目 | J4: 教材・その他 2年目 | K4: 教材・その他 3年目 | L4: 1年目 総額 | M4: 3年継続 総額 | N4: ステモン比 (3年) | O4: 月の授業 時間(分) | P4: 1時間あたり 単価(1年目) | Q4: 月謝レンジ（参考） | R4: 確度
A5: 自社 | B5: ステモン（自社） | C5: 小1ベーシック→小2アドバンス→小3キッズエリート。施設管理費880円/月、2年目以降は年度更新料2,200円＋ロボコン参加費5,500円 | D5: 16500 | E5: 10780 | F5: 10780 | G5: 11880 | H5: 880 | I5: 0 | J5: 7700 | K5: 7700 | L5: =D5+(E5+H5)*12+I5 -> 156420 | M5: =D5+(E5+F5+G5+3*H5)*12+I5+J5+K5 -> 464860 | N5: =M5/$M$5 -> 1 | O5: 200 | P5: =IF(O5="","—",(E5+H5)/(O5/60)) -> 3498 | Q5: 8,580〜11,880円（＋施設費880〜2,200円） | R5: 要確認（入会金16,500/5,500円、施設費880/2,200円で情報が食い違う）
A6: ロボット・ものづくり | B6: STEAM Campus（旧レゴスクール） | C6: 月謝は平均値11,100円、教材は毎年3万円（1〜4.7万円の中央値）と仮定。設備費・指導関連費は除く | D6: 25300 | E6: 11100 | F6: 11100 | G6: 11100 | H6: 0 | I6: 30000 | J6: 30000 | K6: 30000 | L6: =D6+(E6+H6)*12+I6 -> 188500 | M6: =D6+(E6+F6+G6+3*H6)*12+I6+J6+K6 -> 514900 | N6: =M6/$M$5 -> 1.1076453 | P6: =IF(O6="","—",(E6+H6)/(O6/60)) -> — | Q6: 平均 約11,100円（年齢で段階的に上昇） | R6: 要確認（月謝は二次情報の平均値）
A7: ロボット・ものづくり | B7: ヒューマンアカデミー ロボット教室 | C7: 月謝11,550円（2024年11月改定後）、入会時キット33,000円、進級時の追加キット2万円（仮定） | D7: 11000 | E7: 11550 | F7: 11550 | G7: 11550 | H7: 0 | I7: 33000 | J7: 20000 | K7: 0 | L7: =D7+(E7+H7)*12+I7 -> 182600 | M7: =D7+(E7+F7+G7+3*H7)*12+I7+J7+K7 -> 479800 | N7: =M7/$M$5 -> 1.0321387 | O7: 180 | P7: =IF(O7="","—",(E7+H7)/(O7/60)) -> 3850 | Q7: 全コース一律11,550円 | R7: 二次（追加キット額は要確認）
A8: ロボット・ものづくり | B8: ロボ団 | C8: 月謝は9,800〜15,800円の幅があるため、スタータークラス12,750円で代表計算。教材は貸与（レンタル料・タブレット代は含まず） | D8: 11000 | E8: 12750 | F8: 12750 | G8: 12750 | H8: 0 | I8: 0 | J8: 0 | K8: 0 | L8: =D8+(E8+H8)*12+I8 -> 164000 | M8: =D8+(E8+F8+G8+3*H8)*12+I8+J8+K8 -> 470000 | N8: =M8/$M$5 -> 1.0110571 | P8: =IF(O8="","—",(E8+H8)/(O8/60)) -> — | Q8: 9,800〜15,800円（コースで異なる） | R8: 要確認（出典で月謝・レンタル料の扱いが食い違う）
A9: ロボット・ものづくり | B9: クレファス（Crefus） | C9: 小3ブロンズで入会。月謝17,600円＋維持費1,210円、入会時教材67,815円。小4の追加キット代は不明のため含まず | D9: 16500 | E9: 18810 | F9: 18810 | G9: 18810 | H9: 0 | I9: 67815 | J9: 0 | K9: 0 | L9: =D9+(E9+H9)*12+I9 -> 310035 | M9: =D9+(E9+F9+G9+3*H9)*12+I9+J9+K9 -> 761475 | N9: =M9/$M$5 -> 1.6380738 | O9: 315 | P9: =IF(O9="","—",(E9+H9)/(O9/60)) -> 3582.8571 | Q9: Kicks 11,000円／本科 17,600円＋維持費1,210円 | R9: 要確認（別サイトは年約15万円と試算しており大きく食い違う）
A10: ロボット・ものづくり | B10: アーテック エジソンアカデミー | C10: 入会金11,000円、キット4万円（2年分）、月謝11,000円。3年目エキスパート編の教材費は不明のため含まず | D10: 11000 | E10: 11000 | F10: 11000 | G10: 11000 | H10: 0 | I10: 40000 | J10: 0 | K10: 0 | L10: =D10+(E10+H10)*12+I10 -> 183000 | M10: =D10+(E10+F10+G10+3*H10)*12+I10+J10+K10 -> 447000 | N10: =M10/$M$5 -> 0.96157983 | O10: 180 | P10: =IF(O10="","—",(E10+H10)/(O10/60)) -> 3666.6667 | Q10: 8,000〜12,000円程度（教室ごと、本部は非公表） | R10: 二次（教室差が大きい）
A11: ロボット・ものづくり | B11: プログラボ | C11: 入会金・教材費0円。ビギナー→スタンダードII→アドバンストと1年ごとに進級 | D11: 0 | E11: 11770 | F11: 13750 | G11: 14850 | H11: 0 | I11: 0 | J11: 0 | K11: 0 | L11: =D11+(E11+H11)*12+I11 -> 141240 | M11: =D11+(E11+F11+G11+3*H11)*12+I11+J11+K11 -> 484440 | N11: =M11/$M$5 -> 1.0421202 | O11: 150 | P11: =IF(O11="","—",(E11+H11)/(O11/60)) -> 4708 | Q11: 11,770〜14,850円 | R11: 二次（教室で若干差）
A12: ロボット・ものづくり | B12: タミヤロボットスクール | C12: 入会金1万円、月謝7,150円、教材1年目20,350円・2年目13,200円、3年目は2年目と同額と仮置き | D12: 10000 | E12: 7150 | F12: 7150 | G12: 7150 | H12: 0 | I12: 20350 | J12: 13200 | K12: 13200 | L12: =D12+(E12+H12)*12+I12 -> 116150 | M12: =D12+(E12+F12+G12+3*H12)*12+I12+J12+K12 -> 314150 | N12: =M12/$M$5 -> 0.67579486 | O12: 180 | P12: =IF(O12="","—",(E12+H12)/(O12/60)) -> 2383.3333 | Q12: 6,500〜8,500円 | R12: 二次（教室ごと、3年目教材は仮置き）
A13: プログラミング特化 | B13: LITALICOワンダー | C13: 基本コース月4回29,700円、教材費は月謝に含む。入会金16,500円（二次） | D13: 16500 | E13: 29700 | F13: 29700 | G13: 29700 | H13: 0 | I13: 0 | J13: 0 | K13: 0 | L13: =D13+(E13+H13)*12+I13 -> 372900 | M13: =D13+(E13+F13+G13+3*H13)*12+I13+J13+K13 -> 1085700 | N13: =M13/$M$5 -> 2.3355419 | O13: 360 | P13: =IF(O13="","—",(E13+H13)/(O13/60)) -> 4950 | Q13: 29,700円〜（エキスパート・3DCG 34,100円〜） | R13: 公式（入会金は二次）
A14: プログラミング特化 | B14: Tech Kids School | C14: 受講費23,210円＋教材費2,200円/月、PC持参。新規受付停止中のため参考値 | D14: 0 | E14: 23210 | F14: 23210 | G14: 23210 | H14: 2200 | I14: 0 | J14: 0 | K14: 0 | L14: =D14+(E14+H14)*12+I14 -> 304920 | M14: =D14+(E14+F14+G14+3*H14)*12+I14+J14+K14 -> 914760 | N14: =M14/$M$5 -> 1.9678183 | O14: 360 | P14: =IF(O14="","—",(E14+H14)/(O14/60)) -> 4235 | Q14: 23,210円＋教材費2,200円（PCレンタル＋4,400円） | R14: 公式（検索抜粋）
A15: プログラミング特化 | B15: QUREOプログラミング教室 | C15: 月謝9,900円（最低価格帯）、教材費0円。入会金は教室ごとで不明のため0円で計算（実際は上乗せ） | D15: 0 | E15: 9900 | F15: 9900 | G15: 9900 | H15: 0 | I15: 0 | J15: 0 | K15: 0 | L15: =D15+(E15+H15)*12+I15 -> 118800 | M15: =D15+(E15+F15+G15+3*H15)*12+I15+J15+K15 -> 356400 | N15: =M15/$M$5 -> 0.76668244 | O15: 240 | P15: =IF(O15="","—",(E15+H15)/(O15/60)) -> 2475 | Q15: 9,900円〜（教室ごと） | R15: 要確認（入会金不明）
A16: オンライン・通信 | B16: Z会プログラミング講座 | C16: みらい講座 with KOOV。ステージ1は6,200円/月（キット代込み）、ステージ2・3は6,500円と仮定 | D16: 0 | E16: 6200 | F16: 6500 | G16: 6500 | H16: 0 | I16: 0 | J16: 0 | K16: 0 | L16: =D16+(E16+H16)*12+I16 -> 74400 | M16: =D16+(E16+F16+G16+3*H16)*12+I16+J16+K16 -> 230400 | N16: =M16/$M$5 -> 0.49563309 | P16: =IF(O16="","—",(E16+H16)/(O16/60)) -> — | Q16: 約6,200円（KOOVキット代込み） | R16: 要確認（新旧で料金表記が異なる）
A17: オンライン・通信 | B17: デジタネ（旧D-SCHOOLオンライン） | C17: 月々プラン4,980円（年間一括なら39,800円/年） | D17: 0 | E17: 4980 | F17: 4980 | G17: 4980 | H17: 0 | I17: 0 | J17: 0 | K17: 0 | L17: =D17+(E17+H17)*12+I17 -> 59760 | M17: =D17+(E17+F17+G17+3*H17)*12+I17+J17+K17 -> 179280 | N17: =M17/$M$5 -> 0.3856645 | P17: =IF(O17="","—",(E17+H17)/(O17/60)) -> — | Q17: 3,317〜4,980円 | R17: 公式（検索抜粋）
A18: オンライン・通信 | B18: CodeCampKIDS | C18: 教室：ロボットコース1年→Scratchコース2年。教材費は不明のため含まず | D18: 11000 | E18: 11000 | F18: 16500 | G18: 16500 | H18: 0 | I18: 0 | J18: 0 | K18: 0 | L18: =D18+(E18+H18)*12+I18 -> 143000 | M18: =D18+(E18+F18+G18+3*H18)*12+I18+J18+K18 -> 539000 | N18: =M18/$M$5 -> 1.1594889 | P18: =IF(O18="","—",(E18+H18)/(O18/60)) -> — | Q18: 11,000〜16,500円（Online+ 約6,600円） | R18: 二次（教材費不明）
A20: 注記
A21: ・Tech Kids School は新規受付停止中のため参考値。QUREOは入会金不明（0円で計算）。ロボ団はレンタル料・タブレット代を含まない。
A22: ・クレファスは小4の追加キット、エジソンアカデミーは3年目の教材費が不明のため含まない（実際はさらに高い）。
A23: ・1時間あたり単価＝（月謝＋月額諸費用）÷月の授業時間。授業時間が不明・通信型は「—」。
A24: ・オンライン・通信系（Z会・デジタネ）は講師の対面指導がないため、単純な価格比較には注意。

Sheet レッスン・教材
A1: レッスン内容・使用教材
A2: クラス人数は講師1人あたりの目安を含む
A4: 分類 | B4: 社名 | C4: 対象 | D4: 時間・回数 | E4: クラス人数・講師比 | F4: カリキュラム・コース構成 | G4: 大会・検定との接続 | H4: 振替 | I4: 保護者へのフィードバック | J4: 使用教材 | K4: 購入／貸与・持ち帰り
A5: 自社 | B5: ステモン（自社） | C5: 年中〜小6（プロロボは小4〜中学生程度） | D5: 幼児：月2回（年24回）／小学生：60分×年40回（月3〜4回） | E5: 定員 幼児4名・小学生6名（講師1名） | F5: 「しる→つくる→ためす」。手順書なしのコンストラクショニズム型。低学年はブロックで物理（てこ・歯車）＋プログラミング基礎、高学年はPCでゲーム制作・ロボット制御 | G5: 小学生ロボコン公式予選「ステモンカップ」を自社主催（全国大会へ代表派遣） | H5: 教室ごとに可否が異なる（要確認） | I5: 保護者向けSTEAMセミナーあり。毎回のレポート有無は要確認 | J5: 独自カリキュラム＋ブロック教材＋PC（製品名は要確認） | K5: 教室で貸出（購入不要）。PCレンタル2,200円/月
A6: ロボット・ものづくり | B6: STEAM Campus（旧レゴスクール） | C6: 2歳〜中学生（中心は年少〜小学生） | D6: 未就学児50分／小学生90分（月の回数は要確認） | E6: 定員4名〜6〜8名（教室で差、要確認） | F6: 年齢別の1年単位コース（Early Brick→Explorer→Creator→Quester→Investigator→Young Engineer…） | G6: 目立つ大会接続なし（要確認） | H6: 要確認 | I6: 要確認 | J6: LEGO Education（既製品） | K6: 家庭用教材を毎年購入（年1〜4.7万円）
A7: ロボット・ものづくり | B7: ヒューマンアカデミー ロボット教室 | C7: 年中〜高校生相当 | D7: 90分×月2回（1か月で1体のロボットを製作） | E7: 最大10名程度（要確認） | F7: プレプライマリー→プライマリー→ベーシック→ミドル→アドバンス→研究コース。標準キットを最長8年使用 | G7: ロボット教室全国大会（アイデアコンテスト等） | H7: 可（条件は教室次第） | I7: 授業の最後の発表（体系的な報告は要確認） | J7: 独自ロボットキット（高橋智隆氏監修） | K7: 購入制・持ち帰り可
A8: ロボット・ものづくり | B8: ロボ団 | C8: 年長〜中学生 | D8: 年長50分×月3回／小学生90〜120分程度 | E8: メイン講師＋サポート1〜3名体制 | F8: KINDER/WONDER→BEGINNER→CHALLENGER→CREATOR→INNOVATOR。2人1組のペア学習＋毎回の発表 | G8: 社内大会ダンリーグ／ダンカップ、WRO等の世界大会実績（要確認） | H8: 振替・補講あり | I8: 独自アプリで学習状況を保護者も確認、授業見学いつでも可 | J8: LEGO Education SPIKE Prime＋独自テキスト | K8: 教室で貸与（持ち帰り不可）、家庭用タブレットが必要な場合あり
A9: ロボット・ものづくり | B9: クレファス（Crefus） | C9: 年長〜高校生（年長〜小2はKicks） | D9: Kicks 50分×年40回／本科 90分×年42回 | E9: 要確認 | F9: 学年別1年単位のテーマ（ブロンズ：レスキュー・相撲ロボ等）。理科・算数・社会と連動 | G9: FLL認定プラチナスクール。2026年5月のFLL世界大会（ギリシャ）に日本代表として出場。WROにも参加 | H9: 要確認 | I9: 要確認 | J9: LEGOベース（LEGO Education/マインドストーム系）＋独自テキスト | K9: 購入制（年長・小1・小3・小4の節目で買い足し）
A10: ロボット・ものづくり | B10: アーテック エジソンアカデミー | C10: 小3以上（低学年は姉妹コース「自考力キッズ」） | D10: 90分×月2回（教室により60分×3回も） | E10: 講師1人に生徒4〜5人 | F10: 2年制（毎月1体ロボット製作）＋任意の3年目エキスパート編。学年別コースなし | G10: 年1回程度のロボット大会（詳細は要確認） | H10: 教室ごと | I10: 教室ごと | J10: 自社製アーテックロボ／Studuino（Scratchベース） | K10: 買い取り制・持ち帰り可
A11: ロボット・ものづくり | B11: プログラボ | C11: 年長〜中学生 | D11: 50分または90分×月3回 | E11: 1クラス約10名に講師約3名 | F11: ビギナー→スタンダード→アドバンスト→エクスプローラー。最後に発表、宿題なし | G11: 校内「プログラボカップ」、WRO出場を全体でサポート | H11: あり（同一週内） | I11: 見学可（成長レポート等は要確認） | J11: LEGO Education SPIKE Prime／EV3、micro:bit、Scratch | K11: 教室で貸与（持ち帰り不可）
A12: ロボット・ものづくり | B12: タミヤロボットスクール | C12: 小学生（下限学年は教室ごと） | D12: 90分×月2回（年24回） | E12: 要確認 | F12: ロボットプログラミングコース（IchigoJamでBASICのテキスト入力）／メカニックコース（タミヤ工作キット） | G12: 自由製作コンテスト（春・秋）、カムロボダンスコンテスト | H12: 教室ごと | I12: 教室ごと | J12: タミヤ工作キット＋IchigoJam（既製品） | K12: 購入制・持ち帰り可
A13: プログラミング特化 | B13: LITALICOワンダー | C13: 年長〜高3 | D13: 90分×月4回〜 | E13: スタッフ1人に子ども1〜4人 | F13: ゲーム&アプリ、ロボット、デジタルファブリケーション、3DCG、マイクラ等。個別指導計画で進行 | G13: 年2回の発表会（ワンダーメイクフェス） | H13: あり（教室は当日8:59まで連絡） | I13: 保護者フィードバック・個別指導計画あり | J13: Scratch／Viscuit→HTML/JS、LEGO SPIKE、3Dプリンタ・レーザーカッター | K13: 教室備品（月謝込み）
A14: プログラミング特化 | B14: Tech Kids School | C14: 小学生 | D14: 120分×月3回 | E14: 3〜6人のグループにメンター1名 | F14: QUREOで基礎→Scratch/Swift/Unityでアプリ・ゲーム開発 | G14: 自社主催 Tech Kids Grand Prix（賞金総額100万円） | H14: あり | I14: 半年に1度の成果発表会 | J14: QUREO、Scratch、Swift、Unity | K14: PC持参 or レンタル
A15: プログラミング特化 | B15: QUREOプログラミング教室 | C15: 小2〜中学生 | D15: 60分×月4回（教室ごと） | E15: 教室ごと（要確認） | F15: 自学自習型のオンライン教材。ビジュアル→テキストプログラミング、マイクラコース。200以上のレッスン | G15: プログラミング能力検定に準拠 | H15: 自宅からオンライン振替可 | I15: 保護者専用ページで進捗を可視化 | J15: 独自オンライン教材QUREO＋教育版マインクラフト | K15: アカウント型（PC等は教室備品が多い）
... A18: オンライン・通信 | B18: CodeCampKIDS | C18: 年長〜中学生 | D18: 1回90分（月の回数は要確認） | E18: オンラインは5名程度（教室は要確認） | F18: ScratchJr→Scratch→ロボット（toio、Sphero）→Unity | G18: ジュニア・プログラミング検定対応（要確認） | H18: 要確認 | I18: オンラインは課題へのフィードバックあり | J18: ScratchJr、Scratch、toio、Sphero Mini、Unity | K18: 要確認

Sheet 講師
A1: 先生の質（募集要項・口コミ）
A2: 時給は求人サイトの掲載例。FC中心のブランドは加盟事業者ごとに条件が異なる
A4: 分類 | B4: 社名 | C4: 雇用形態 | D4: 時給・給与 | E4: 応募条件 | F4: 研修制度 | G4: 講師1人あたり生徒数 | H4: 口コミ傾向（良い点／不満点）
A5: 自社 | B5: ステモン（自社） | C5: パート・アルバイト（正社員の教室運営職も募集） | D5: 1コマ2,000〜2,700円（時給換算 約1,330〜1,800円）／研修時給1,170〜1,240円 | E5: 未経験可・週1日〜 | F5: 座学＋実地研修 2か月、マニュアルあり | G5: 1:4（幼児）／1:6（小学生） | H5: 子どもが楽しく通える、思考力の伸びを実感／個別に見てもらえる時間が少ない
A6: ロボット・ものづくり | B6: STEAM Campus（旧レゴスクール） | C6: アルバイト・パート | D6: 時給1,200〜1,600円（研修1,120円の例） | E6: 未経験可・学歴不問 | F6: 要確認 | G6: 4〜8名程度（推定） | H6: 質の高いプログラム／運営会社で品質差の懸念
A7: ロボット・ものづくり | B7: ヒューマンアカデミー ロボット教室 | C7: 業務委託講師 | D7: 時給1,320円〜 | E7: 未経験可・大学生/社会人のWワーク歓迎 | F7: FC本部の研修・マニュアル（オーナー向け） | G7: 〜10名（推定） | H7: ヒントを出して考えさせる／講師の対応が教室によってばらつく
A8: ロボット・ものづくり | B8: ロボ団 | C8: アルバイト（サポート講師） | D8: 要確認 | E8: プログラミング知識不要・学生歓迎 | F8: 要確認 | G8: 1〜3名体制（クラス人数は要確認） | H8: 明るく探究心を刺激／グループ授業で個々の理解度が見えにくい
A9: ロボット・ものづくり | B9: クレファス（Crefus） | C9: アルバイト講師 | D9: 時給2,000円以上 | E9: 文系・理系不問 | F9: 研修制度あり、指導力に応じて上位クラスを担当 | G9: 要確認 | H9: ハキハキして気持ちがよい／講師がプログラミングに詳しくない場合も
A10: ロボット・ものづくり | B10: アーテック エジソンアカデミー | C10: 加盟教室ごとに採用 | D10: 要確認 | E10: 要確認 | F10: 加盟時の本部研修（詳細は要確認） | G10: 1:4〜5 | H10: 少人数でしっかり見てもらえる／塾スタッフが兼任し教室差が出やすい
A11: ロボット・ものづくり | B11: プログラボ | C11: アルバイト（学生歓迎） | D11: 時給1,100〜2,000円、研修時給1,200円〜 | E11: 未経験・学生歓迎、週1日〜 | F11: 研修期間 最大3か月 | G11: 1:3〜4 | H11: 優しく熱心／学生講師でばらつき（すぐ正解を教える等）
A12: ロボット・ものづくり | B12: タミヤロボットスクール | C12: 加盟事業者ごとに採用 | D12: 要確認 | E12: 要確認 | F12: 要確認 | G12: 要確認 | H12: 口コミ件数自体が少ない
A13: プログラミング特化 | B13: LITALICOワンダー | C13: 正社員中心＋研修済みアルバイト | D13: アルバイト時給1,230〜1,500円 | E13: 資格・経験不問 | F13: 先輩社員との1on1・教室会議（体系的研修の詳細は要確認） | G13: 1:1〜4 | H13: 先生の質が高い、発達特性のある子も楽しく通える／担当の先生が毎回変わる
A14: プログラミング特化 | B14: Tech Kids School | C14: 学生スタッフ（大学生・院生メンター） | D14: 要確認 | E14: 資格・経験不要 | F14: 選考・研修を経て認定（二次） | G14: 1:3〜6 | H14: 大学生メンターで話しやすい／すぐ答えを教えない方針がもどかしい
A15: プログラミング特化 | B15: QUREOプログラミング教室 | C15: 加盟塾の講師 | D15: 時給1,300〜1,680円程度（求人例） | E15: 未経験可 | F15: 本部研修の内容は要確認 | G15: 教室ごと（要確認） | H15: すぐ質問できる／教室で先生の質がまちまち、自習を見守るだけ
... A18: オンライン・通信 | B18: CodeCampKIDS | C18: アルバイト | D18: 時給1,200〜1,500円以上 | E18: 未経験可 | F18: 研修あり | G18: 要確認 | H18: 優しく丁寧／講師によって指導レベルに差

Sheet 口コミ・課題
A1: 口コミ傾向・考えられる課題・ステモンの攻めどころ
A2: 口コミはコエテコ・塾ナビ・オリコン・ブログ等の傾向を要約
A4: 分類 | B4: 社名 | C4: 褒められている点 | D4: 不満が多い点 | E4: 考えられる課題（弱み） | F4: ステモンが攻められるポイント | G4: 脅威度
A5: 自社 | B5: ステモン（自社） | C5: 体験型で夢中になる、ものの仕組みから学べる、ロボコンに出られる、オリコン顧客満足度 ロボット部門6位（76.4点） | D5: 料金が他より高め、個別指導が少ない、地方に教室が少ない、教室で振替ルールが違う | E5: オンライン系の2〜3倍の価格。FCで品質・ルールがばらつく。小4以降の出口（本格的なコード）が薄い。料金表示が情報源でばらつく | F5: — | G5: —
A6: ロボット・ものづくり | B6: STEAM Campus（旧レゴスクール） | C6: 独自性の高いプログラム、幼児期から始められる、商業施設内で通いやすい | D6: 月謝が高い、教材を毎年購入する必要があり割高感、体験が有料、「LEGO」ブランド喪失による混乱 | E6: 2024年にLEGOブランドを失い認知低下。教材の毎年購入で総額が見えにくい。運営会社が複数で品質・料金にばらつき | F6: ブランド一貫性と独自カリキュラム、教材購入不要＝総額の分かりやすさ、小学校高学年まで続く一貫性を訴求 | G6: 中
A7: ロボット・ものづくり | B7: ヒューマンアカデミー ロボット教室 | C7: 教室が多く近所にある、ロボットがかっこよく夢中になる、テキストが充実、全国大会、月2回で続けやすい | D7: 初期費用・月謝が高い、講師の質が教室でばらつく、組み立て中心でプログラミングが少ない、月2回では物足りない | E7: 業務委託・未経験可の講師で品質がばらつく。テキスト通りの組み立て中心。月2回で接触回数が少ない | F7: 講師研修と品質の均一さ、「自分で考えて作る」探究型、月あたりの授業回数・時間の多さで比較訴求 | G7: 高
A8: ロボット・ものづくり | B8: ロボ団 | C8: ペアワークと発表でプレゼン力がつく、教材購入不要、アプリで学習状況が分かる、大会がある | D8: 月謝が高め、作品を持ち帰れない、隠れ費用（タブレット・施設費）、個々の理解度が見えにくい | E8: 成果物が家に残らず保護者が成長を実感しにくい。料金体系が分かりにくい。規模の開示が2022年で止まっている | F8: 作品の持ち帰り・保護者向けの成長の見える化、総額の透明性、工作×ロボット×プログラミングの幅の広さ | G8: 中
A9: ロボット・ものづくり | B9: クレファス（Crefus） | C9: 本格的なカリキュラム、FLL等の大会実績が豊富、中高生まで続けられる、教科と連動 | D9: 費用が高い（月謝＋教材の買い足し）、節目で教材を買い直す、少人数教室では大会に出られない | E9: 3年総額が最も高い部類（推定70万円超）。大会志向で上級者向けの印象。教材の買い替え負担 | F9: コスパ（3年総額）での比較、「大会志向ではない子」「ものづくり好き」の受け皿。※講師採用では時給2,000円超で強い競合 | G9: 中
A10: ロボット・ものづくり | B10: アーテック エジソンアカデミー | C10: 料金が比較的安い、少人数、毎月ロボットが完成する達成感、持ち帰って家で遊べる | D10: キット代（約4万円）、開講日時が少ない教室も、料金がHPになく分かりにくい | E10: 対象が小3以上中心。2年で一巡し3年目以降は任意。FCで講師の熱量・専門性が教室依存。料金非公開 | F10: 年中〜低学年からの一貫性、長期継続カリキュラム、講師品質、総額の透明性、素材・工作まで扱うSTEAMの幅 | G10: 中
A11: ロボット・ものづくり | B11: プログラボ | C11: 入会金・教材費0円、駅近で通いやすい、講師が多く質問しやすい、WROへの道 | D11: 上位コースは月1.5万円近い、教材を持ち帰れない、学生講師の質のばらつき | E11: LEGO既製品を組む中心。持ち帰り不可。学生講師中心でばらつき。鉄道沿線に立地が偏る | F11: 身近な素材を使ったものづくり・仕組み理解、作品の持ち帰り、講師品質の見える化、沿線外エリアでの出店 | G11: 高
A12: ロボット・ものづくり | B12: タミヤロボットスクール | C12: 月謝が業界最安クラス、タミヤブランドの安心感、本物の工作（ギア・モーター）、早期にテキストプログラミング | D12: 口コミが少なく判断しにくい、教室により片方のコースのみ、教室数が少ない、低学年にはテキスト入力が難しい | E12: 教室数が少なく知名度はタミヤ頼み。低学年・未就学への対応が弱い。キット組立中心で自由な発想の比重は限定的 | F12: 年中〜低学年からの一貫性、創造・表現（STEAMのA）。価格ではなく内容密度・講師品質で比較軸を作る | G12: 低
A13: プログラミング特化 | B13: LITALICOワンダー | C13: 先生の質・子ども理解、少人数・個別対応、好きを伸ばす自由度、設備が充実 | D13: 料金が業界最高水準、月4回前提で隔週通いができない、担当講師が固定でない、首都圏のみ | E13: 月3万円前後で家計負担大。拠点が少ない。自由創作型で「何が身についたか」が見えにくい | F13: LITALICO並みの少人数・探究型を低価格・地域密着で。体系的カリキュラムの見える化、担当講師制 | G13: 低
A14: プログラミング特化 | B14: Tech Kids School | C14: 本格度（アプリ公開・大会入賞）、発表文化、サイバーエージェントブランド | D14: 料金が高い、渋谷1拠点のみ、女子が少ない、現在は入学できない | E14: 新規受付停止（事業縮小・QUREOへのシフトの可能性）。拠点が渋谷のみ。画面内学習に偏る | F14: 「本格的に学びたいが入れない」層の受け皿。外部大会に挑戦できる上位コース | G14: 低
A15: プログラミング特化 | B15: QUREOプログラミング教室 | C15: 月1万円前後で安い、教材費無料、近所の塾で通える、ゲーム感覚、進捗が見える、検定で成果が形に | D15: 教室によって質がばらつく、自学自習で教わる感が薄い、画面内のみでものづくりなし | E15: 加盟塾ごとの講師品質差。画面内完結でハンズオン・協働が少ない。教室体験は塾依存 | F15: 手を動かすハンズオンSTEAMで差別化、講師主導の対話型授業、小2未満の受け皿。加盟塾への提案では併設商材として比較される点に注意 | G15: 中
... A18: オンライン・通信 | B18: CodeCampKIDS | C18: 1か月お試しできる、教室がきれい、Unityまで進める出口の高さ | D18: 上位コースの月謝16,500円は高額、講師による差、教室数が少ない | E18: 教室数40強で首都圏中心。上位コースが高額。物理・ものづくり要素は薄い | F18: 幼児からのものづくりの厚み、教室網の広さ | G18: 低

Sheet ポジショニング
A1: ポジショニング（価格 × 学びのスタイル）
A2: 体験スコア：1＝画面内で完結するプログラミング／5＝実物を使ったものづくり・仕組み理解（定性評価、青字は書き換え可）
A4: 分類 | B4: 社名 | C4: 3年総額（試算） | D4: 体験スコア(1-5) | E4: 対象年齢の下限 | F4: 脅威度
A5: 自社 | B5: ステモン（自社） | C5: =料金比較!M5 -> 464860 | D5: 5 | E5: 年中 | F5: —
A6: ロボット・ものづくり | B6: STEAM Campus（旧レゴスクール） | C6: =料金比較!M6 -> 514900 | D6: 4.5 | E6: 2歳 | F6: 中
A7: ロボット・ものづくり | B7: ヒューマンアカデミー ロボット教室 | C7: =料金比較!M7 -> 479800 | D7: 4 | E7: 年中 | F7: 高
A8: ロボット・ものづくり | B8: ロボ団 | C8: =料金比較!M8 -> 470000 | D8: 3.5 | E8: 年長 | F8: 中
A9: ロボット・ものづくり | B9: クレファス（Crefus） | C9: =料金比較!M9 -> 761475 | D9: 3.5 | E9: 年長 | F9: 中
A10: ロボット・ものづくり | B10: アーテック エジソンアカデミー | C10: =料金比較!M10 -> 447000 | D10: 4 | E10: 小3 | F10: 中
A11: ロボット・ものづくり | B11: プログラボ | C11: =料金比較!M11 -> 484440 | D11: 3.5 | E11: 年長 | F11: 高
A12: ロボット・ものづくり | B12: タミヤロボットスクール | C12: =料金比較!M12 -> 314150 | D12: 4.5 | E12: 小学生 | F12: 低
A13: プログラミング特化 | B13: LITALICOワンダー | C13: =料金比較!M13 -> 1085700 | D13: 3 | E13: 年長 | F13: 低
A14: プログラミング特化 | B14: Tech Kids School | C14: =料金比較!M14 -> 914760 | D14: 1.5 | E14: 小1 | F14: 低
A15: プログラミング特化 | B15: QUREOプログラミング教室 | C15: =料金比較!M15 -> 356400 | D15: 1 | E15: 小2 | F15: 中
A16: オンライン・通信 | B16: Z会プログラミング講座 | C16: =料金比較!M16 -> 230400 | D16: 3 | E16: 年長 | F16: 低
... A18: オンライン・通信 | B18: CodeCampKIDS | C18: =料金比較!M18 -> 539000 | D18: 2 | E18: 年長 | F18: 低
A20: 読み取り：「3年40〜50万円 × ものづくり寄り」にステモン・ヒューマンアカデミー・エジソンアカデミー・プログラボ・STEAM Campusが集中。価格帯内での差別化軸（講師品質・成果の見える化・年中からの一貫性）が重要。

Sheet ステモン戦略
A1: ステモンのSWOTと提言
A2: 競合比較の結果から導出（社内検討用のたたき台）
A4: 強み（Strength） | C4: 弱み（Weakness）
A5: S1 | B5: 年中から通えるSTEAM（物理の仕組み＋ものづくり＋プログラミング） | C5: W1 | D5: 月謝＋諸費用で年15万円前後（オンライン系の2〜3倍）
A6: S2 | B6: 少人数（幼児4名・小学生6名）の対面授業 | C6: W2 | D6: FCで振替ルール・講師品質が教室ごとにばらつく
A7: S3 | B7: 教材は教室で貸出＝購入不要で初期費用が低い | C7: W3 | D7: 講師は未経験可のアルバイト中心
A8: S4 | B8: 小学生ロボコン公式予選「ステモンカップ」を自社主催 | C8: W4 | D8: 小4以降の本格コード（Python/Unity等）の出口が薄い
A9: S5 | B9: 170教室超、出店継続（学童・フリースクールへも展開） | C9: W5 | D9: 入会金・施設費の表示が情報源でばらつき、総額が分かりにくい
A11: 機会（Opportunity） | C11: 脅威（Threat）
A12: O1 | B12: STEAM Campusの「LEGOブランド喪失」で幼児層が流動化 | C12: T1 | D12: ヒューマンアカデミー（2,000教室超）、QUREO（3,000教室超）の規模と塾併設FCの拡大
A13: O2 | B13: Tech Kids Schoolの新規受付停止、Z会の講座縮小で受け皿需要 | C13: T2 | D13: プログラボの入会金・教材費0円モデル
A14: O3 | B14: ロボ団・プログラボは作品を持ち帰れない→「成果の見える化」で差別化余地 | C14: T3 | D14: クレファス（時給2,000円超）等との講師採用競争
A15: O4 | B15: 競合の多くが総額非公開・教材の買い足しあり→総額の透明化で優位 | C15: T4 | D15: オンライン系（年4〜7万円）の低価格化
A16: O5 | B16: 沿線・首都圏外の空白エリア（LITALICO・プログラボ・CodeCampKIDSは偏在） | C16: T5 | D16: 競合の大会実績（クレファスのFLL世界大会等）による上位層の流出
A19: 領域 | B19: 打ち手 | C19: 優先度 | D19: 期間の目安
A20: 料金 | B20: 「3年総額」の公式提示と、競合との総額比較表を体験会で配布。入会金・施設費の表記を全教室で統一 | C20: 高 | D20: 〜3か月
A21: カリキュラム | B21: 小4〜6向けの出口（テキストコーディング・外部大会挑戦コース）を強化し、高学年の退会を防ぐ | C21: 高 | D21: 6〜12か月
A22: 講師品質 | B22: 研修2か月・グレード制を「講師品質の約束」として外部に発信。FC教室を含めた授業品質チェックを定例化 | C22: 中 | D22: 〜6か月
A23: 成果の見える化 | B23: 作品持ち帰り＋毎回の保護者レポート（写真・コメント）を標準化し、ロボ団・プログラボとの差別化軸にする | C23: 高 | D23: 〜3か月
A24: 集客・ターゲット | B24: STEAM Campus・Tech Kids・Z会からの流出層向けキャンペーン（乗り換え入会金免除など） | C24: 中 | D24: 〜3か月
A25: 出店 | B25: 沿線外・地方の空白エリアを競合マップで特定し、FC開拓の優先エリアに設定 | C25: 中 | D25: 6〜12か月
A26: パートナー | B26: ナリカ等の教材サプライヤーとの教材調達・学校連携（公教育）の協業を検討 | C26: 低 | D26: 12か月〜

Sheet 要確認リスト
A1: 要確認リスト（公式ページ等で確認が必要な項目）
A2: 確認したら「状態」を更新し、該当シートの値を修正する
A4: No | B4: 対象 | C4: 確認項目 | D4: 現在の値・状況 | E4: 確認先 | F4: 優先度 | G4: 状態
A5: 1 | B5: ステモン | C5: 入会金・施設管理費の正しい金額 | D5: 入会金16,500円 or 5,500円／施設費880円 or 2,200円で情報が食い違う | E5: 社内（料金表） | F5: 高 | G5: 未確認
A6: 2 | B6: ステモン | C6: プログラミング＆ロボティクス（小4〜）の月謝 | D6: 未取得 | E6: 社内（料金表） | F6: 高 | G6: 未確認
A7: 3 | B7: ステモン | C7: 振替ルール・保護者レポートの有無・教材製品名 | D7: 教室ごとに異なる（要確認） | E7: 社内 | F7: 中 | G7: 未確認
A8: 4 | B8: STEAM Campus | C8: コース別の月謝、設備費・指導関連費、月の回数、教室総数 | D8: 月謝は二次情報の平均値11,100円 | E8: steamcampus.jp／各運営会社サイト | F8: 高 | G8: 未確認
A9: 5 | B9: ヒューマンアカデミー | C9: 現在のキット代・進級時の追加キット額 | D9: 33,000円（旧31,350円）、追加は約1〜2.6万円と食い違い | E9: kids.athuman.com/robo/ | F9: 中 | G9: 未確認
A10: 6 | B10: ロボ団 | C10: コース別月謝、教材レンタル料・タブレット代の有無、最新教室数、講師時給 | D10: 月謝9,800〜15,800円で出典が食い違う | E10: robo-done.com | F10: 高 | G10: 未確認
A11: 7 | B11: クレファス | C11: コース別月謝、追加キット額、定員 | D11: 3年総額が別サイト試算（年約15万円）と大きく食い違う | E11: crefus.jp／近隣教室 | F11: 高 | G11: 未確認
A12: 8 | B12: エジソンアカデミー | C12: 最新教室数、3年目教材費、講師募集条件 | D12: 教室数は2021年頃の約850〜900 | E12: artec-kk.co.jp | F12: 中 | G12: 未確認
A13: 9 | B13: プログラボ | C13: 2026年時点の校数、保護者向けフィードバック制度 | D13: 84校（2024年9月） | E13: proglab.education | F13: 中 | G13: 未確認
A14: 10 | B14: タミヤロボットスクール | C14: 最新教室数、対象学年の下限、クラス人数、3年目教材費 | D14: 約100教室（古い） | E14: tamiya-robotschool.com | F14: 低 | G14: 未確認
A15: 11 | B15: LITALICOワンダー | C15: 入会金16,500円、生徒数約5,050名の時点 | D15: 入会金は二次情報 | E15: wonder.litalico.jp | F15: 低 | G15: 未確認
A16: 12 | B16: Tech Kids School | C16: 新規受付停止の開始時期・理由・再開予定 | D16: 公式に「受付停止」の記載 | E16: techkidsschool.jp | F16: 中 | G16: 未確認
... A21: 17 | B21: 全社 | C21: 講師1人あたり生徒数の公式値、口コミ評価点（コエテコ・塾ナビ）の最新値 | D21: 一部のみ取得 | E21: 各社サイト・口コミサイト | F21: 中 | G21: 未確認

Sheet 参考_ナリカ・その他
A1: 株式会社ナリカ（参考：教材サプライヤー）
A2: 子ども向け教室の運営事業者ではない（運営・提携スクールの事実は確認できず）。学校向け理科・プログラミング教材の製造販売会社で、STEAMスクールにとっては「教材の仕入れ先」。
A4: 項目 | B4: 内容
A5: 会社概要 | B5: 1918年創業（中村理科機器店）、2008年に「ナリカ」へ社名変更。本社：東京都千代田区外神田。従業員88名（2025年5月）
A6: 事業 | B6: 小中高・大学向け理科教材・実験機器の企画・製造・販売（理科ドットコム rika.com）、EC「scibox」
A7: プログラミング教材 | B7: LEGO Education 正規販売代理店（SPIKE プライム／ベーシック等）、micro:bitシリーズ、小6理科「電気の利用」向けセット
A8: 教員向け研修 | B8: ナリカサイエンスアカデミー（NSA）：教員向け理科実験実技講習。受講料 教員2,000円／学生1,000円（1講座）
A9: 価格帯（参考） | B9: SPIKE プライム基本セット 約68,000〜75,000円（他販売店）。ナリカの価格は未確認
A10: ステモンとの関係 | B10: 競合ではなく、①理科実験・LEGO/micro:bit教材の調達先、②教員研修ノウハウ・講師人材との接点、③学校向け販路（公教育連携）のパートナー候補
A12: その他 注視すべき教室
A13: 名称 | B13: 概要 | C13: URL
A14: KOOVパートナー教室（ソニー・グローバルエデュケーション） | B14: KOOVを使うライセンス型の教室網。全国1,000教室以上との記載（要確認） | C14: https://www.koov.io/
A15: もののしくみ研究室／しくみKids（学研） | B15: 学研のロボットプログラミング講座。加盟教室型 | C15: https://robot.gakken.jp/school

Sheet 出典
A1: 出典一覧
A2: 確認日：2026-09-28（すべて検索結果の要約で確認。本文の直接閲覧は未実施）
A4: 社名 | B4: URL
A5: ステモン（自社） | B5: https://www.stemon.net/cources-prices/
A6: ステモン（自社） | B6: https://www.dreamnews.jp/press/0000342672
A7: ステモン（自社） | B7: https://coeteco.jp/brand/stemon
A8: ステモン（自社） | B8: https://juken.oricon.co.jp/rank-kids-programming/company/stemon/
A9: ステモン（自社） | B9: https://en-gage.net/viling/work_6029651/
A10: STEAM Campus（旧レゴスクール） | B10: https://steamcampus.jp/
A11: STEAM Campus（旧レゴスクール） | B11: https://www.learningsystems.co.jp/steam_campus_fc.html
A12: STEAM Campus（旧レゴスクール） | B12: https://manabikids.jp/lego-gessha/
A13: STEAM Campus（旧レゴスクール） | B13: https://coeteco.jp/brand/legoschool
A14: ヒューマンアカデミー ロボット教室 | B14: https://kids.athuman.com/robo/
A15: ヒューマンアカデミー ロボット教室 | B15: https://kids.athuman.com/fc/lp02/
... A59: 株式会社ナリカ（参考：教材サプライヤー） | B59: https://www.rika.com/nsa
